redset/__init__.py
redset/exceptions.py
redset/interfaces.py
redset/locks.py
redset/serializers.py
redset/sets.py
redset-0.5.1.dist-info/DESCRIPTION.rst
redset-0.5.1.dist-info/METADATA
redset-0.5.1.dist-info/metadata.json
redset-0.5.1.dist-info/RECORD
redset-0.5.1.dist-info/top_level.txt
redset-0.5.1.dist-info/WHEEL
