Metadata-Version: 2.0
Name: redset
Version: 0.5.1
Summary: Simple, distributed sorted sets with redis
Home-page: https://github.com/percolate/redset
Author: thekantian, jamesob
Author-email: zach@percolate.com, jamesob@percolate.com
License: see LICENSE
Platform: UNKNOWN
Classifier: Intended Audience :: Developers
Classifier: License :: OSI Approved :: BSD License
Classifier: Operating System :: OS Independent
Classifier: Programming Language :: Python :: 2.7
Classifier: Programming Language :: Python :: 3
Classifier: Topic :: Software Development :: Libraries :: Python Modules
